pwnic/BaseAttacker.py
pwnic/__init__.py
pwnic/__main__.py
pwnic/api.py
pwnic/config.py
pwnic/db.py
pwnic/exploits.py
pwnic/logger.py
pwnic/submitter.py
pwnic/utils.py
pwnic-0.5.0.dist-info/LICENSE
pwnic-0.5.0.dist-info/METADATA
pwnic-0.5.0.dist-info/WHEEL
pwnic-0.5.0.dist-info/RECORD
