Metadata-Version: 2.1
Name: pwnic
Version: 0.5.0
Summary: Awesome `pwnic` is a Python cli/package created with https://github.com/TezRomacH/python-package-template
Home-page: https://github.com/pwnic/pwnic
License: GNU GPL v3.0
Author: pwnic
Author-email: francesco.basile12@studenti.unina.it
Requires-Python: >=3.11,<4.0
Classifier: Development Status :: 3 - Alpha
Classifier: Intended Audience :: Developers
Classifier: License :: OSI Approved :: GNU General Public License v3 or later (GPLv3+)
Classifier: License :: Other/Proprietary License
Classifier: Operating System :: OS Independent
Classifier: Programming Language :: Python :: 3
Classifier: Programming Language :: Python :: 3.11
Classifier: Topic :: Software Development :: Libraries :: Python Modules
Requires-Dist: colorlog (>=6.7.0,<7.0.0)
Requires-Dist: fastapi (>=0.100.0,<0.101.0)
Requires-Dist: jsonschema (>=4.18.2,<5.0.0)
Requires-Dist: python-multipart (>=0.0.6,<0.0.7)
Requires-Dist: requests (>=2.31.0,<3.0.0)
Requires-Dist: rfc3987 (>=1.3.8,<2.0.0)
Requires-Dist: rich (>=13.4.2,<14.0.0)
Project-URL: Repository, https://github.com/pwnic/pwnic
